correcthorse/__init__.py
correcthorse/__main__.py
correcthorse/plurals.py
correcthorse/words/words_en.txt
correcthorse-0.2.0.dist-info/METADATA
correcthorse-0.2.0.dist-info/RECORD
correcthorse-0.2.0.dist-info/WHEEL
correcthorse-0.2.0.dist-info/entry_points.txt
correcthorse-0.2.0.dist-info/top_level.txt
