Metadata-Version: 2.1
Name: correcthorse
Version: 0.2.0
Summary: Secure but memorable passphrase generator
Home-page: https://github.com/nickovs/correcthorse
Author: Nicko van Someren
Author-email: nicko@nicko.org
License: UNKNOWN
Keywords: password,passphrase
Platform: UNKNOWN
Classifier: Development Status :: 3 - Alpha
Classifier: Programming Language :: Python :: 3
Classifier: License :: OSI Approved :: Apache Software License
Classifier: Operating System :: OS Independent
Requires-Python: >=3.4
